logging_loki/__init__.py
logging_loki/const.py
logging_loki/emitter.py
logging_loki/handlers.py
python_logging_loki-0.3.1.dist-info/LICENSE
python_logging_loki-0.3.1.dist-info/METADATA
python_logging_loki-0.3.1.dist-info/WHEEL
python_logging_loki-0.3.1.dist-info/top_level.txt
python_logging_loki-0.3.1.dist-info/RECORD
