Metadata-Version: 2.1
Name: python-logging-loki
Version: 0.3.1
Summary: Python logging handler for Grafana Loki.
Home-page: https://github.com/greyzmeem/python-logging-loki
Author: Andrey Maslov
Author-email: greyzmeem@gmail.com
License: MIT
Platform: UNKNOWN
Classifier: Development Status :: 4 - Beta
Classifier: Intended Audience :: Developers
Classifier: License :: OSI Approved :: MIT License
Classifier: Operating System :: OS Independent
Classifier: Programming Language :: Python
Classifier: Programming Language :: Python :: 3
Classifier: Programming Language :: Python :: 3.6
Classifier: Programming Language :: Python :: 3.7
Classifier: Programming Language :: Python :: 3.8
Classifier: Topic :: Software Development :: Libraries :: Python Modules
Classifier: Topic :: System :: Logging
Classifier: Topic :: Internet :: WWW/HTTP
Requires-Python: >=3.6
